{
  "version": "nail-texture-dataset/v1",
  "decision": "candidate_only_not_training_truth",
  "image": {
    "id": "deerplanet.tw_189738136_817755759122324_6566260232266868061_n_196209916560de93328e40c",
    "fileName": "deerplanet.tw_189738136_817755759122324_6566260232266868061_n_196209916560de93328e40c.jpg",
    "width": 800,
    "height": 800,
    "sourceGroup": "real-reference-2026-07-12-batch-02",
    "negative": false
  },
  "annotations": [
    {
      "id": "n1",
      "label": "nail_texture",
      "polygon": [
        {
          "x": 260.0,
          "y": 569.0
        },
        {
          "x": 260.0,
          "y": 588.0
        },
        {
          "x": 266.0,
          "y": 588.0
        },
        {
          "x": 266.0,
          "y": 583.0
        },
        {
          "x": 265.0,
          "y": 582.0
        },
        {
          "x": 265.0,
          "y": 580.0
        },
        {
          "x": 264.0,
          "y": 579.0
        },
        {
          "x": 264.0,
          "y": 577.0
        },
        {
          "x": 263.0,
          "y": 576.0
        },
        {
          "x": 263.0,
          "y": 574.0
        },
        {
          "x": 262.0,
          "y": 573.0
        },
        {
          "x": 262.0,
          "y": 572.0
        },
        {
          "x": 260.0,
          "y": 570.0
        },
        {
          "x": 260.0,
          "y": 569.0
        },
        {
          "x": 271.0,
          "y": 557.0
        },
        {
          "x": 279.0,
          "y": 565.0
        },
        {
          "x": 279.0,
          "y": 566.0
        },
        {
          "x": 284.0,
          "y": 571.0
        },
        {
          "x": 284.0,
          "y": 572.0
        },
        {
          "x": 291.0,
          "y": 579.0
        },
        {
          "x": 291.0,
          "y": 580.0
        },
        {
          "x": 293.0,
          "y": 582.0
        },
        {
          "x": 293.0,
          "y": 583.0
        },
        {
          "x": 295.0,
          "y": 585.0
        },
        {
          "x": 295.0,
          "y": 586.0
        },
        {
          "x": 297.0,
          "y": 588.0
        },
        {
          "x": 357.0,
          "y": 588.0
        },
        {
          "x": 359.0,
          "y": 586.0
        },
        {
          "x": 359.0,
          "y": 585.0
        },
        {
          "x": 364.0,
          "y": 580.0
        },
        {
          "x": 364.0,
          "y": 579.0
        },
        {
          "x": 365.0,
          "y": 578.0
        },
        {
          "x": 366.0,
          "y": 578.0
        },
        {
          "x": 366.0,
          "y": 577.0
        },
        {
          "x": 370.0,
          "y": 573.0
        },
        {
          "x": 370.0,
          "y": 572.0
        },
        {
          "x": 371.0,
          "y": 571.0
        },
        {
          "x": 371.0,
          "y": 525.0
        },
        {
          "x": 370.0,
          "y": 524.0
        },
        {
          "x": 370.0,
          "y": 523.0
        },
        {
          "x": 367.0,
          "y": 520.0
        },
        {
          "x": 366.0,
          "y": 520.0
        },
        {
          "x": 363.0,
          "y": 517.0
        },
        {
          "x": 363.0,
          "y": 516.0
        },
        {
          "x": 358.0,
          "y": 511.0
        },
        {
          "x": 358.0,
          "y": 510.0
        },
        {
          "x": 354.0,
          "y": 506.0
        },
        {
          "x": 354.0,
          "y": 505.0
        },
        {
          "x": 349.0,
          "y": 500.0
        },
        {
          "x": 349.0,
          "y": 499.0
        },
        {
          "x": 342.0,
          "y": 492.0
        },
        {
          "x": 342.0,
          "y": 491.0
        },
        {
          "x": 335.0,
          "y": 484.0
        },
        {
          "x": 334.0,
          "y": 484.0
        },
        {
          "x": 332.0,
          "y": 482.0
        },
        {
          "x": 260.0,
          "y": 482.0
        },
        {
          "x": 260.0,
          "y": 541.0
        },
        {
          "x": 266.0,
          "y": 547.0
        },
        {
          "x": 266.0,
          "y": 548.0
        },
        {
          "x": 267.0,
          "y": 549.0
        },
        {
          "x": 267.0,
          "y": 550.0
        },
        {
          "x": 268.0,
          "y": 551.0
        },
        {
          "x": 268.0,
          "y": 552.0
        },
        {
          "x": 269.0,
          "y": 553.0
        },
        {
          "x": 269.0,
          "y": 554.0
        },
        {
          "x": 271.0,
          "y": 556.0
        },
        {
          "x": 271.0,
          "y": 557.0
        }
      ],
      "attributes": {
        "fingerHint": "unknown",
        "shape": "unknown",
        "quality": 2,
        "occluded": false,
        "artificialTip": false,
        "annotationMethod": "yolo-real-seed-prelabel",
        "confidence": 0.331162,
        "reviewRequired": true
      }
    },
    {
      "id": "n2",
      "label": "nail_texture",
      "polygon": [
        {
          "x": 322.0,
          "y": 279.0
        },
        {
          "x": 322.0,
          "y": 415.0
        },
        {
          "x": 323.0,
          "y": 415.0
        },
        {
          "x": 324.0,
          "y": 416.0
        },
        {
          "x": 325.0,
          "y": 416.0
        },
        {
          "x": 327.0,
          "y": 418.0
        },
        {
          "x": 332.0,
          "y": 418.0
        },
        {
          "x": 333.0,
          "y": 419.0
        },
        {
          "x": 336.0,
          "y": 419.0
        },
        {
          "x": 337.0,
          "y": 420.0
        },
        {
          "x": 342.0,
          "y": 420.0
        },
        {
          "x": 344.0,
          "y": 418.0
        },
        {
          "x": 345.0,
          "y": 418.0
        },
        {
          "x": 346.0,
          "y": 417.0
        },
        {
          "x": 347.0,
          "y": 418.0
        },
        {
          "x": 349.0,
          "y": 418.0
        },
        {
          "x": 350.0,
          "y": 419.0
        },
        {
          "x": 352.0,
          "y": 419.0
        },
        {
          "x": 353.0,
          "y": 420.0
        },
        {
          "x": 427.0,
          "y": 420.0
        },
        {
          "x": 446.0,
          "y": 401.0
        },
        {
          "x": 446.0,
          "y": 400.0
        },
        {
          "x": 450.0,
          "y": 396.0
        },
        {
          "x": 450.0,
          "y": 395.0
        },
        {
          "x": 452.0,
          "y": 393.0
        },
        {
          "x": 452.0,
          "y": 392.0
        },
        {
          "x": 460.0,
          "y": 384.0
        },
        {
          "x": 460.0,
          "y": 382.0
        },
        {
          "x": 461.0,
          "y": 381.0
        },
        {
          "x": 461.0,
          "y": 380.0
        },
        {
          "x": 462.0,
          "y": 379.0
        },
        {
          "x": 462.0,
          "y": 331.0
        },
        {
          "x": 459.0,
          "y": 328.0
        },
        {
          "x": 459.0,
          "y": 327.0
        },
        {
          "x": 458.0,
          "y": 326.0
        },
        {
          "x": 458.0,
          "y": 322.0
        },
        {
          "x": 457.0,
          "y": 321.0
        },
        {
          "x": 457.0,
          "y": 314.0
        },
        {
          "x": 456.0,
          "y": 313.0
        },
        {
          "x": 456.0,
          "y": 312.0
        },
        {
          "x": 455.0,
          "y": 311.0
        },
        {
          "x": 455.0,
          "y": 310.0
        },
        {
          "x": 454.0,
          "y": 309.0
        },
        {
          "x": 454.0,
          "y": 303.0
        },
        {
          "x": 452.0,
          "y": 301.0
        },
        {
          "x": 452.0,
          "y": 295.0
        },
        {
          "x": 453.0,
          "y": 294.0
        },
        {
          "x": 454.0,
          "y": 295.0
        },
        {
          "x": 458.0,
          "y": 295.0
        },
        {
          "x": 459.0,
          "y": 296.0
        },
        {
          "x": 461.0,
          "y": 294.0
        },
        {
          "x": 462.0,
          "y": 294.0
        },
        {
          "x": 462.0,
          "y": 279.0
        }
      ],
      "attributes": {
        "fingerHint": "unknown",
        "shape": "unknown",
        "quality": 2,
        "occluded": false,
        "artificialTip": false,
        "annotationMethod": "yolo-real-seed-prelabel",
        "confidence": 0.22201,
        "reviewRequired": true
      }
    },
    {
      "id": "n3",
      "label": "nail_texture",
      "polygon": [
        {
          "x": 202.0,
          "y": 477.0
        },
        {
          "x": 201.0,
          "y": 478.0
        },
        {
          "x": 201.0,
          "y": 480.0
        },
        {
          "x": 200.0,
          "y": 481.0
        },
        {
          "x": 200.0,
          "y": 483.0
        },
        {
          "x": 199.0,
          "y": 484.0
        },
        {
          "x": 199.0,
          "y": 485.0
        },
        {
          "x": 196.0,
          "y": 488.0
        },
        {
          "x": 195.0,
          "y": 488.0
        },
        {
          "x": 194.0,
          "y": 489.0
        },
        {
          "x": 193.0,
          "y": 489.0
        },
        {
          "x": 191.0,
          "y": 491.0
        },
        {
          "x": 190.0,
          "y": 491.0
        },
        {
          "x": 189.0,
          "y": 492.0
        },
        {
          "x": 189.0,
          "y": 493.0
        },
        {
          "x": 186.0,
          "y": 496.0
        },
        {
          "x": 186.0,
          "y": 497.0
        },
        {
          "x": 184.0,
          "y": 499.0
        },
        {
          "x": 180.0,
          "y": 499.0
        },
        {
          "x": 179.0,
          "y": 500.0
        },
        {
          "x": 178.0,
          "y": 500.0
        },
        {
          "x": 174.0,
          "y": 504.0
        },
        {
          "x": 173.0,
          "y": 504.0
        },
        {
          "x": 173.0,
          "y": 629.0
        },
        {
          "x": 185.0,
          "y": 629.0
        },
        {
          "x": 186.0,
          "y": 628.0
        },
        {
          "x": 187.0,
          "y": 628.0
        },
        {
          "x": 188.0,
          "y": 627.0
        },
        {
          "x": 189.0,
          "y": 627.0
        },
        {
          "x": 190.0,
          "y": 626.0
        },
        {
          "x": 191.0,
          "y": 626.0
        },
        {
          "x": 192.0,
          "y": 625.0
        },
        {
          "x": 193.0,
          "y": 625.0
        },
        {
          "x": 195.0,
          "y": 623.0
        },
        {
          "x": 196.0,
          "y": 623.0
        },
        {
          "x": 197.0,
          "y": 622.0
        },
        {
          "x": 198.0,
          "y": 622.0
        },
        {
          "x": 199.0,
          "y": 621.0
        },
        {
          "x": 200.0,
          "y": 621.0
        },
        {
          "x": 201.0,
          "y": 620.0
        },
        {
          "x": 202.0,
          "y": 620.0
        },
        {
          "x": 208.0,
          "y": 614.0
        },
        {
          "x": 210.0,
          "y": 614.0
        },
        {
          "x": 211.0,
          "y": 613.0
        },
        {
          "x": 216.0,
          "y": 613.0
        },
        {
          "x": 217.0,
          "y": 614.0
        },
        {
          "x": 220.0,
          "y": 614.0
        },
        {
          "x": 221.0,
          "y": 615.0
        },
        {
          "x": 222.0,
          "y": 615.0
        },
        {
          "x": 224.0,
          "y": 617.0
        },
        {
          "x": 225.0,
          "y": 617.0
        },
        {
          "x": 227.0,
          "y": 619.0
        },
        {
          "x": 228.0,
          "y": 619.0
        },
        {
          "x": 235.0,
          "y": 626.0
        },
        {
          "x": 237.0,
          "y": 626.0
        },
        {
          "x": 238.0,
          "y": 627.0
        },
        {
          "x": 239.0,
          "y": 627.0
        },
        {
          "x": 241.0,
          "y": 629.0
        },
        {
          "x": 294.0,
          "y": 629.0
        },
        {
          "x": 293.0,
          "y": 628.0
        },
        {
          "x": 293.0,
          "y": 627.0
        },
        {
          "x": 294.0,
          "y": 626.0
        },
        {
          "x": 294.0,
          "y": 623.0
        },
        {
          "x": 295.0,
          "y": 622.0
        },
        {
          "x": 295.0,
          "y": 614.0
        },
        {
          "x": 296.0,
          "y": 613.0
        },
        {
          "x": 296.0,
          "y": 612.0
        },
        {
          "x": 299.0,
          "y": 609.0
        },
        {
          "x": 299.0,
          "y": 608.0
        },
        {
          "x": 301.0,
          "y": 606.0
        },
        {
          "x": 301.0,
          "y": 605.0
        },
        {
          "x": 302.0,
          "y": 604.0
        },
        {
          "x": 302.0,
          "y": 603.0
        },
        {
          "x": 303.0,
          "y": 602.0
        },
        {
          "x": 303.0,
          "y": 601.0
        },
        {
          "x": 305.0,
          "y": 599.0
        },
        {
          "x": 305.0,
          "y": 598.0
        },
        {
          "x": 307.0,
          "y": 596.0
        },
        {
          "x": 307.0,
          "y": 595.0
        },
        {
          "x": 308.0,
          "y": 594.0
        },
        {
          "x": 308.0,
          "y": 593.0
        },
        {
          "x": 309.0,
          "y": 592.0
        },
        {
          "x": 313.0,
          "y": 592.0
        },
        {
          "x": 314.0,
          "y": 591.0
        },
        {
          "x": 319.0,
          "y": 591.0
        },
        {
          "x": 320.0,
          "y": 590.0
        },
        {
          "x": 321.0,
          "y": 590.0
        },
        {
          "x": 326.0,
          "y": 595.0
        },
        {
          "x": 326.0,
          "y": 477.0
        }
      ],
      "attributes": {
        "fingerHint": "unknown",
        "shape": "unknown",
        "quality": 2,
        "occluded": false,
        "artificialTip": false,
        "annotationMethod": "yolo-real-seed-prelabel",
        "confidence": 0.189362,
        "reviewRequired": true
      }
    },
    {
      "id": "n4",
      "label": "nail_texture",
      "polygon": [
        {
          "x": 272.0,
          "y": 519.0
        },
        {
          "x": 272.0,
          "y": 620.0
        },
        {
          "x": 277.0,
          "y": 620.0
        },
        {
          "x": 279.0,
          "y": 618.0
        },
        {
          "x": 279.0,
          "y": 617.0
        },
        {
          "x": 280.0,
          "y": 616.0
        },
        {
          "x": 280.0,
          "y": 615.0
        },
        {
          "x": 282.0,
          "y": 613.0
        },
        {
          "x": 282.0,
          "y": 612.0
        },
        {
          "x": 283.0,
          "y": 611.0
        },
        {
          "x": 283.0,
          "y": 610.0
        },
        {
          "x": 285.0,
          "y": 608.0
        },
        {
          "x": 285.0,
          "y": 607.0
        },
        {
          "x": 286.0,
          "y": 606.0
        },
        {
          "x": 286.0,
          "y": 605.0
        },
        {
          "x": 290.0,
          "y": 601.0
        },
        {
          "x": 291.0,
          "y": 602.0
        },
        {
          "x": 296.0,
          "y": 602.0
        },
        {
          "x": 305.0,
          "y": 611.0
        },
        {
          "x": 306.0,
          "y": 611.0
        },
        {
          "x": 315.0,
          "y": 620.0
        },
        {
          "x": 360.0,
          "y": 620.0
        },
        {
          "x": 360.0,
          "y": 619.0
        },
        {
          "x": 361.0,
          "y": 618.0
        },
        {
          "x": 361.0,
          "y": 617.0
        },
        {
          "x": 362.0,
          "y": 616.0
        },
        {
          "x": 362.0,
          "y": 615.0
        },
        {
          "x": 364.0,
          "y": 613.0
        },
        {
          "x": 364.0,
          "y": 612.0
        },
        {
          "x": 366.0,
          "y": 610.0
        },
        {
          "x": 366.0,
          "y": 609.0
        },
        {
          "x": 368.0,
          "y": 607.0
        },
        {
          "x": 368.0,
          "y": 606.0
        },
        {
          "x": 369.0,
          "y": 605.0
        },
        {
          "x": 369.0,
          "y": 604.0
        },
        {
          "x": 370.0,
          "y": 603.0
        },
        {
          "x": 370.0,
          "y": 602.0
        },
        {
          "x": 372.0,
          "y": 600.0
        },
        {
          "x": 372.0,
          "y": 599.0
        },
        {
          "x": 378.0,
          "y": 593.0
        },
        {
          "x": 379.0,
          "y": 594.0
        },
        {
          "x": 381.0,
          "y": 594.0
        },
        {
          "x": 382.0,
          "y": 595.0
        },
        {
          "x": 382.0,
          "y": 536.0
        },
        {
          "x": 376.0,
          "y": 530.0
        },
        {
          "x": 375.0,
          "y": 530.0
        },
        {
          "x": 373.0,
          "y": 528.0
        },
        {
          "x": 372.0,
          "y": 528.0
        },
        {
          "x": 369.0,
          "y": 525.0
        },
        {
          "x": 369.0,
          "y": 524.0
        },
        {
          "x": 364.0,
          "y": 519.0
        }
      ],
      "attributes": {
        "fingerHint": "unknown",
        "shape": "unknown",
        "quality": 2,
        "occluded": false,
        "artificialTip": false,
        "annotationMethod": "yolo-real-seed-prelabel",
        "confidence": 0.162244,
        "reviewRequired": true
      }
    }
  ]
}