{
  "version": "nail-texture-dataset/v1",
  "image": {
    "id": "-2023-08-06-19.32.21_22532801864cf8588659e3-1017x1024",
    "fileName": "-2023-08-06-19.32.21_22532801864cf8588659e3-1017x1024.jpg",
    "width": 1017,
    "height": 1024,
    "sourceGroup": "real-reference-2026-07-12-batch-02",
    "negative": false
  },
  "annotations": [
    {
      "id": "n1",
      "label": "nail_texture",
      "polygon": [
        {
          "x": 114,
          "y": 442
        },
        {
          "x": 113,
          "y": 443
        },
        {
          "x": 112,
          "y": 443
        },
        {
          "x": 111,
          "y": 444
        },
        {
          "x": 110,
          "y": 444
        },
        {
          "x": 109,
          "y": 445
        },
        {
          "x": 108,
          "y": 445
        },
        {
          "x": 106,
          "y": 447
        },
        {
          "x": 106,
          "y": 448
        },
        {
          "x": 105,
          "y": 449
        },
        {
          "x": 105,
          "y": 450
        },
        {
          "x": 104,
          "y": 451
        },
        {
          "x": 104,
          "y": 452
        },
        {
          "x": 100,
          "y": 456
        },
        {
          "x": 100,
          "y": 457
        },
        {
          "x": 94,
          "y": 463
        },
        {
          "x": 93,
          "y": 463
        },
        {
          "x": 89,
          "y": 467
        },
        {
          "x": 89,
          "y": 468
        },
        {
          "x": 88,
          "y": 469
        },
        {
          "x": 88,
          "y": 470
        },
        {
          "x": 86,
          "y": 472
        },
        {
          "x": 86,
          "y": 473
        },
        {
          "x": 81,
          "y": 478
        },
        {
          "x": 81,
          "y": 479
        },
        {
          "x": 78,
          "y": 482
        },
        {
          "x": 78,
          "y": 483
        },
        {
          "x": 76,
          "y": 485
        },
        {
          "x": 76,
          "y": 486
        },
        {
          "x": 74,
          "y": 488
        },
        {
          "x": 74,
          "y": 489
        },
        {
          "x": 72,
          "y": 491
        },
        {
          "x": 72,
          "y": 492
        },
        {
          "x": 71,
          "y": 493
        },
        {
          "x": 71,
          "y": 494
        },
        {
          "x": 69,
          "y": 496
        },
        {
          "x": 69,
          "y": 497
        },
        {
          "x": 67,
          "y": 499
        },
        {
          "x": 66,
          "y": 499
        },
        {
          "x": 60,
          "y": 505
        },
        {
          "x": 59,
          "y": 505
        },
        {
          "x": 57,
          "y": 507
        },
        {
          "x": 56,
          "y": 507
        },
        {
          "x": 56,
          "y": 558
        },
        {
          "x": 61,
          "y": 563
        },
        {
          "x": 61,
          "y": 564
        },
        {
          "x": 64,
          "y": 567
        },
        {
          "x": 64,
          "y": 568
        },
        {
          "x": 71,
          "y": 575
        },
        {
          "x": 71,
          "y": 576
        },
        {
          "x": 85,
          "y": 590
        },
        {
          "x": 86,
          "y": 590
        },
        {
          "x": 89,
          "y": 593
        },
        {
          "x": 90,
          "y": 593
        },
        {
          "x": 91,
          "y": 594
        },
        {
          "x": 92,
          "y": 594
        },
        {
          "x": 96,
          "y": 598
        },
        {
          "x": 97,
          "y": 598
        },
        {
          "x": 99,
          "y": 600
        },
        {
          "x": 135,
          "y": 600
        },
        {
          "x": 136,
          "y": 599
        },
        {
          "x": 137,
          "y": 599
        },
        {
          "x": 138,
          "y": 598
        },
        {
          "x": 139,
          "y": 598
        },
        {
          "x": 143,
          "y": 594
        },
        {
          "x": 144,
          "y": 594
        },
        {
          "x": 146,
          "y": 592
        },
        {
          "x": 147,
          "y": 592
        },
        {
          "x": 148,
          "y": 591
        },
        {
          "x": 149,
          "y": 591
        },
        {
          "x": 154,
          "y": 586
        },
        {
          "x": 154,
          "y": 585
        },
        {
          "x": 159,
          "y": 580
        },
        {
          "x": 159,
          "y": 579
        },
        {
          "x": 160,
          "y": 578
        },
        {
          "x": 160,
          "y": 577
        },
        {
          "x": 161,
          "y": 576
        },
        {
          "x": 161,
          "y": 574
        },
        {
          "x": 162,
          "y": 573
        },
        {
          "x": 162,
          "y": 501
        },
        {
          "x": 161,
          "y": 500
        },
        {
          "x": 161,
          "y": 499
        },
        {
          "x": 160,
          "y": 498
        },
        {
          "x": 160,
          "y": 497
        },
        {
          "x": 159,
          "y": 496
        },
        {
          "x": 159,
          "y": 494
        },
        {
          "x": 158,
          "y": 493
        },
        {
          "x": 158,
          "y": 492
        },
        {
          "x": 157,
          "y": 491
        },
        {
          "x": 157,
          "y": 490
        },
        {
          "x": 156,
          "y": 489
        },
        {
          "x": 156,
          "y": 488
        },
        {
          "x": 155,
          "y": 487
        },
        {
          "x": 155,
          "y": 486
        },
        {
          "x": 153,
          "y": 484
        },
        {
          "x": 153,
          "y": 483
        },
        {
          "x": 152,
          "y": 482
        },
        {
          "x": 152,
          "y": 481
        },
        {
          "x": 151,
          "y": 480
        },
        {
          "x": 151,
          "y": 479
        },
        {
          "x": 149,
          "y": 477
        },
        {
          "x": 149,
          "y": 476
        },
        {
          "x": 148,
          "y": 475
        },
        {
          "x": 148,
          "y": 474
        },
        {
          "x": 143,
          "y": 469
        },
        {
          "x": 143,
          "y": 468
        },
        {
          "x": 141,
          "y": 466
        },
        {
          "x": 141,
          "y": 465
        },
        {
          "x": 127,
          "y": 451
        },
        {
          "x": 127,
          "y": 450
        },
        {
          "x": 125,
          "y": 448
        },
        {
          "x": 125,
          "y": 447
        },
        {
          "x": 123,
          "y": 445
        },
        {
          "x": 122,
          "y": 445
        },
        {
          "x": 121,
          "y": 444
        },
        {
          "x": 120,
          "y": 444
        },
        {
          "x": 119,
          "y": 443
        },
        {
          "x": 118,
          "y": 443
        },
        {
          "x": 117,
          "y": 442
        }
      ],
      "attributes": {
        "fingerHint": "unknown",
        "shape": "unknown",
        "quality": 4,
        "occluded": false,
        "artificialTip": false,
        "annotationMethod": "vision-reviewed-yolo-real-prelabel-v2",
        "confidence": 0.832738,
        "reviewRequired": false
      }
    },
    {
      "id": "n2",
      "label": "nail_texture",
      "polygon": [
        {
          "x": 243,
          "y": 462
        },
        {
          "x": 238,
          "y": 467
        },
        {
          "x": 237,
          "y": 467
        },
        {
          "x": 236,
          "y": 468
        },
        {
          "x": 236,
          "y": 469
        },
        {
          "x": 234,
          "y": 471
        },
        {
          "x": 234,
          "y": 472
        },
        {
          "x": 230,
          "y": 476
        },
        {
          "x": 230,
          "y": 477
        },
        {
          "x": 224,
          "y": 483
        },
        {
          "x": 224,
          "y": 484
        },
        {
          "x": 222,
          "y": 486
        },
        {
          "x": 222,
          "y": 487
        },
        {
          "x": 221,
          "y": 488
        },
        {
          "x": 221,
          "y": 489
        },
        {
          "x": 219,
          "y": 491
        },
        {
          "x": 219,
          "y": 492
        },
        {
          "x": 218,
          "y": 493
        },
        {
          "x": 218,
          "y": 494
        },
        {
          "x": 217,
          "y": 495
        },
        {
          "x": 217,
          "y": 497
        },
        {
          "x": 216,
          "y": 498
        },
        {
          "x": 216,
          "y": 499
        },
        {
          "x": 215,
          "y": 500
        },
        {
          "x": 215,
          "y": 502
        },
        {
          "x": 214,
          "y": 503
        },
        {
          "x": 214,
          "y": 504
        },
        {
          "x": 213,
          "y": 505
        },
        {
          "x": 213,
          "y": 506
        },
        {
          "x": 212,
          "y": 507
        },
        {
          "x": 212,
          "y": 508
        },
        {
          "x": 210,
          "y": 510
        },
        {
          "x": 210,
          "y": 511
        },
        {
          "x": 208,
          "y": 513
        },
        {
          "x": 208,
          "y": 514
        },
        {
          "x": 207,
          "y": 515
        },
        {
          "x": 207,
          "y": 516
        },
        {
          "x": 206,
          "y": 517
        },
        {
          "x": 206,
          "y": 519
        },
        {
          "x": 205,
          "y": 520
        },
        {
          "x": 205,
          "y": 521
        },
        {
          "x": 204,
          "y": 522
        },
        {
          "x": 204,
          "y": 523
        },
        {
          "x": 203,
          "y": 524
        },
        {
          "x": 203,
          "y": 526
        },
        {
          "x": 202,
          "y": 527
        },
        {
          "x": 202,
          "y": 529
        },
        {
          "x": 201,
          "y": 530
        },
        {
          "x": 201,
          "y": 533
        },
        {
          "x": 200,
          "y": 534
        },
        {
          "x": 200,
          "y": 549
        },
        {
          "x": 201,
          "y": 550
        },
        {
          "x": 201,
          "y": 552
        },
        {
          "x": 202,
          "y": 553
        },
        {
          "x": 202,
          "y": 554
        },
        {
          "x": 204,
          "y": 556
        },
        {
          "x": 204,
          "y": 557
        },
        {
          "x": 206,
          "y": 559
        },
        {
          "x": 206,
          "y": 560
        },
        {
          "x": 207,
          "y": 561
        },
        {
          "x": 207,
          "y": 562
        },
        {
          "x": 211,
          "y": 566
        },
        {
          "x": 211,
          "y": 567
        },
        {
          "x": 214,
          "y": 570
        },
        {
          "x": 214,
          "y": 571
        },
        {
          "x": 216,
          "y": 573
        },
        {
          "x": 216,
          "y": 574
        },
        {
          "x": 219,
          "y": 577
        },
        {
          "x": 219,
          "y": 578
        },
        {
          "x": 222,
          "y": 581
        },
        {
          "x": 222,
          "y": 582
        },
        {
          "x": 231,
          "y": 591
        },
        {
          "x": 231,
          "y": 592
        },
        {
          "x": 238,
          "y": 599
        },
        {
          "x": 239,
          "y": 599
        },
        {
          "x": 240,
          "y": 600
        },
        {
          "x": 288,
          "y": 600
        },
        {
          "x": 289,
          "y": 599
        },
        {
          "x": 289,
          "y": 598
        },
        {
          "x": 291,
          "y": 596
        },
        {
          "x": 291,
          "y": 595
        },
        {
          "x": 293,
          "y": 593
        },
        {
          "x": 293,
          "y": 592
        },
        {
          "x": 295,
          "y": 590
        },
        {
          "x": 295,
          "y": 589
        },
        {
          "x": 296,
          "y": 588
        },
        {
          "x": 296,
          "y": 587
        },
        {
          "x": 297,
          "y": 586
        },
        {
          "x": 297,
          "y": 584
        },
        {
          "x": 298,
          "y": 583
        },
        {
          "x": 298,
          "y": 582
        },
        {
          "x": 299,
          "y": 581
        },
        {
          "x": 299,
          "y": 537
        },
        {
          "x": 298,
          "y": 536
        },
        {
          "x": 298,
          "y": 533
        },
        {
          "x": 297,
          "y": 532
        },
        {
          "x": 297,
          "y": 529
        },
        {
          "x": 296,
          "y": 528
        },
        {
          "x": 296,
          "y": 525
        },
        {
          "x": 295,
          "y": 524
        },
        {
          "x": 295,
          "y": 520
        },
        {
          "x": 294,
          "y": 519
        },
        {
          "x": 294,
          "y": 513
        },
        {
          "x": 293,
          "y": 512
        },
        {
          "x": 293,
          "y": 503
        },
        {
          "x": 292,
          "y": 502
        },
        {
          "x": 292,
          "y": 498
        },
        {
          "x": 291,
          "y": 497
        },
        {
          "x": 291,
          "y": 494
        },
        {
          "x": 290,
          "y": 493
        },
        {
          "x": 290,
          "y": 490
        },
        {
          "x": 289,
          "y": 489
        },
        {
          "x": 289,
          "y": 487
        },
        {
          "x": 288,
          "y": 486
        },
        {
          "x": 288,
          "y": 484
        },
        {
          "x": 287,
          "y": 483
        },
        {
          "x": 287,
          "y": 482
        },
        {
          "x": 286,
          "y": 481
        },
        {
          "x": 286,
          "y": 480
        },
        {
          "x": 285,
          "y": 479
        },
        {
          "x": 285,
          "y": 478
        },
        {
          "x": 284,
          "y": 477
        },
        {
          "x": 284,
          "y": 476
        },
        {
          "x": 282,
          "y": 474
        },
        {
          "x": 282,
          "y": 473
        },
        {
          "x": 279,
          "y": 470
        },
        {
          "x": 279,
          "y": 469
        },
        {
          "x": 278,
          "y": 468
        },
        {
          "x": 278,
          "y": 467
        },
        {
          "x": 276,
          "y": 465
        },
        {
          "x": 276,
          "y": 464
        },
        {
          "x": 274,
          "y": 462
        }
      ],
      "attributes": {
        "fingerHint": "unknown",
        "shape": "unknown",
        "quality": 4,
        "occluded": false,
        "artificialTip": false,
        "annotationMethod": "vision-reviewed-yolo-real-prelabel-v2",
        "confidence": 0.826706,
        "reviewRequired": false
      }
    },
    {
      "id": "n3",
      "label": "nail_texture",
      "polygon": [
        {
          "x": 807,
          "y": 316
        },
        {
          "x": 806,
          "y": 317
        },
        {
          "x": 805,
          "y": 317
        },
        {
          "x": 803,
          "y": 319
        },
        {
          "x": 802,
          "y": 319
        },
        {
          "x": 800,
          "y": 321
        },
        {
          "x": 799,
          "y": 321
        },
        {
          "x": 797,
          "y": 323
        },
        {
          "x": 796,
          "y": 323
        },
        {
          "x": 794,
          "y": 325
        },
        {
          "x": 793,
          "y": 325
        },
        {
          "x": 791,
          "y": 327
        },
        {
          "x": 790,
          "y": 327
        },
        {
          "x": 789,
          "y": 328
        },
        {
          "x": 788,
          "y": 328
        },
        {
          "x": 786,
          "y": 330
        },
        {
          "x": 785,
          "y": 330
        },
        {
          "x": 784,
          "y": 331
        },
        {
          "x": 783,
          "y": 331
        },
        {
          "x": 781,
          "y": 333
        },
        {
          "x": 780,
          "y": 333
        },
        {
          "x": 777,
          "y": 336
        },
        {
          "x": 776,
          "y": 336
        },
        {
          "x": 775,
          "y": 337
        },
        {
          "x": 774,
          "y": 337
        },
        {
          "x": 767,
          "y": 344
        },
        {
          "x": 766,
          "y": 344
        },
        {
          "x": 757,
          "y": 353
        },
        {
          "x": 756,
          "y": 353
        },
        {
          "x": 753,
          "y": 356
        },
        {
          "x": 753,
          "y": 357
        },
        {
          "x": 750,
          "y": 360
        },
        {
          "x": 749,
          "y": 360
        },
        {
          "x": 745,
          "y": 364
        },
        {
          "x": 745,
          "y": 365
        },
        {
          "x": 740,
          "y": 370
        },
        {
          "x": 739,
          "y": 370
        },
        {
          "x": 738,
          "y": 371
        },
        {
          "x": 738,
          "y": 413
        },
        {
          "x": 739,
          "y": 414
        },
        {
          "x": 740,
          "y": 414
        },
        {
          "x": 742,
          "y": 416
        },
        {
          "x": 743,
          "y": 416
        },
        {
          "x": 744,
          "y": 417
        },
        {
          "x": 745,
          "y": 417
        },
        {
          "x": 747,
          "y": 419
        },
        {
          "x": 748,
          "y": 419
        },
        {
          "x": 750,
          "y": 421
        },
        {
          "x": 751,
          "y": 421
        },
        {
          "x": 753,
          "y": 423
        },
        {
          "x": 754,
          "y": 423
        },
        {
          "x": 755,
          "y": 424
        },
        {
          "x": 756,
          "y": 424
        },
        {
          "x": 757,
          "y": 425
        },
        {
          "x": 759,
          "y": 425
        },
        {
          "x": 760,
          "y": 426
        },
        {
          "x": 761,
          "y": 426
        },
        {
          "x": 762,
          "y": 427
        },
        {
          "x": 763,
          "y": 427
        },
        {
          "x": 764,
          "y": 428
        },
        {
          "x": 765,
          "y": 428
        },
        {
          "x": 766,
          "y": 429
        },
        {
          "x": 767,
          "y": 429
        },
        {
          "x": 768,
          "y": 430
        },
        {
          "x": 770,
          "y": 430
        },
        {
          "x": 771,
          "y": 431
        },
        {
          "x": 773,
          "y": 431
        },
        {
          "x": 774,
          "y": 432
        },
        {
          "x": 778,
          "y": 432
        },
        {
          "x": 779,
          "y": 433
        },
        {
          "x": 809,
          "y": 433
        },
        {
          "x": 810,
          "y": 432
        },
        {
          "x": 815,
          "y": 432
        },
        {
          "x": 816,
          "y": 431
        },
        {
          "x": 821,
          "y": 431
        },
        {
          "x": 822,
          "y": 430
        },
        {
          "x": 825,
          "y": 430
        },
        {
          "x": 826,
          "y": 429
        },
        {
          "x": 829,
          "y": 429
        },
        {
          "x": 831,
          "y": 427
        },
        {
          "x": 833,
          "y": 427
        },
        {
          "x": 834,
          "y": 426
        },
        {
          "x": 835,
          "y": 426
        },
        {
          "x": 836,
          "y": 425
        },
        {
          "x": 838,
          "y": 425
        },
        {
          "x": 839,
          "y": 424
        },
        {
          "x": 841,
          "y": 424
        },
        {
          "x": 842,
          "y": 423
        },
        {
          "x": 843,
          "y": 423
        },
        {
          "x": 844,
          "y": 422
        },
        {
          "x": 845,
          "y": 422
        },
        {
          "x": 846,
          "y": 421
        },
        {
          "x": 847,
          "y": 421
        },
        {
          "x": 850,
          "y": 418
        },
        {
          "x": 851,
          "y": 418
        },
        {
          "x": 852,
          "y": 417
        },
        {
          "x": 853,
          "y": 417
        },
        {
          "x": 854,
          "y": 416
        },
        {
          "x": 855,
          "y": 416
        },
        {
          "x": 856,
          "y": 415
        },
        {
          "x": 858,
          "y": 415
        },
        {
          "x": 859,
          "y": 414
        },
        {
          "x": 860,
          "y": 414
        },
        {
          "x": 868,
          "y": 406
        },
        {
          "x": 868,
          "y": 338
        },
        {
          "x": 867,
          "y": 337
        },
        {
          "x": 867,
          "y": 336
        },
        {
          "x": 866,
          "y": 335
        },
        {
          "x": 866,
          "y": 333
        },
        {
          "x": 865,
          "y": 332
        },
        {
          "x": 865,
          "y": 331
        },
        {
          "x": 864,
          "y": 330
        },
        {
          "x": 864,
          "y": 329
        },
        {
          "x": 862,
          "y": 327
        },
        {
          "x": 862,
          "y": 326
        },
        {
          "x": 858,
          "y": 322
        },
        {
          "x": 858,
          "y": 321
        },
        {
          "x": 854,
          "y": 317
        },
        {
          "x": 853,
          "y": 317
        },
        {
          "x": 852,
          "y": 316
        }
      ],
      "attributes": {
        "fingerHint": "unknown",
        "shape": "unknown",
        "quality": 4,
        "occluded": false,
        "artificialTip": false,
        "annotationMethod": "vision-reviewed-yolo-real-prelabel-v2",
        "confidence": 0.813233,
        "reviewRequired": false
      }
    },
    {
      "id": "n4",
      "label": "nail_texture",
      "polygon": [
        {
          "x": 400,
          "y": 532
        },
        {
          "x": 400,
          "y": 570
        },
        {
          "x": 400,
          "y": 568
        },
        {
          "x": 401,
          "y": 567
        },
        {
          "x": 401,
          "y": 564
        },
        {
          "x": 402,
          "y": 563
        },
        {
          "x": 402,
          "y": 555
        },
        {
          "x": 401,
          "y": 554
        },
        {
          "x": 401,
          "y": 546
        },
        {
          "x": 400,
          "y": 545
        },
        {
          "x": 400,
          "y": 532
        },
        {
          "x": 413,
          "y": 527
        },
        {
          "x": 414,
          "y": 528
        },
        {
          "x": 414,
          "y": 531
        },
        {
          "x": 415,
          "y": 532
        },
        {
          "x": 415,
          "y": 534
        },
        {
          "x": 416,
          "y": 535
        },
        {
          "x": 416,
          "y": 537
        },
        {
          "x": 417,
          "y": 538
        },
        {
          "x": 417,
          "y": 539
        },
        {
          "x": 418,
          "y": 540
        },
        {
          "x": 418,
          "y": 541
        },
        {
          "x": 419,
          "y": 542
        },
        {
          "x": 419,
          "y": 543
        },
        {
          "x": 421,
          "y": 545
        },
        {
          "x": 421,
          "y": 547
        },
        {
          "x": 422,
          "y": 548
        },
        {
          "x": 422,
          "y": 550
        },
        {
          "x": 423,
          "y": 551
        },
        {
          "x": 423,
          "y": 552
        },
        {
          "x": 424,
          "y": 553
        },
        {
          "x": 424,
          "y": 554
        },
        {
          "x": 425,
          "y": 555
        },
        {
          "x": 425,
          "y": 556
        },
        {
          "x": 427,
          "y": 558
        },
        {
          "x": 427,
          "y": 559
        },
        {
          "x": 432,
          "y": 564
        },
        {
          "x": 432,
          "y": 565
        },
        {
          "x": 436,
          "y": 569
        },
        {
          "x": 437,
          "y": 569
        },
        {
          "x": 438,
          "y": 570
        },
        {
          "x": 462,
          "y": 570
        },
        {
          "x": 463,
          "y": 569
        },
        {
          "x": 464,
          "y": 569
        },
        {
          "x": 465,
          "y": 568
        },
        {
          "x": 466,
          "y": 568
        },
        {
          "x": 467,
          "y": 567
        },
        {
          "x": 468,
          "y": 567
        },
        {
          "x": 476,
          "y": 559
        },
        {
          "x": 476,
          "y": 512
        },
        {
          "x": 475,
          "y": 511
        },
        {
          "x": 475,
          "y": 508
        },
        {
          "x": 474,
          "y": 507
        },
        {
          "x": 474,
          "y": 506
        },
        {
          "x": 473,
          "y": 505
        },
        {
          "x": 473,
          "y": 503
        },
        {
          "x": 472,
          "y": 502
        },
        {
          "x": 472,
          "y": 500
        },
        {
          "x": 471,
          "y": 499
        },
        {
          "x": 471,
          "y": 497
        },
        {
          "x": 470,
          "y": 496
        },
        {
          "x": 470,
          "y": 494
        },
        {
          "x": 469,
          "y": 493
        },
        {
          "x": 469,
          "y": 492
        },
        {
          "x": 468,
          "y": 491
        },
        {
          "x": 468,
          "y": 490
        },
        {
          "x": 464,
          "y": 486
        },
        {
          "x": 464,
          "y": 485
        },
        {
          "x": 463,
          "y": 484
        },
        {
          "x": 463,
          "y": 483
        },
        {
          "x": 461,
          "y": 481
        },
        {
          "x": 461,
          "y": 480
        },
        {
          "x": 460,
          "y": 479
        },
        {
          "x": 460,
          "y": 478
        },
        {
          "x": 456,
          "y": 474
        },
        {
          "x": 456,
          "y": 473
        },
        {
          "x": 452,
          "y": 469
        },
        {
          "x": 452,
          "y": 468
        },
        {
          "x": 444,
          "y": 460
        },
        {
          "x": 444,
          "y": 459
        },
        {
          "x": 442,
          "y": 457
        },
        {
          "x": 442,
          "y": 456
        },
        {
          "x": 439,
          "y": 453
        },
        {
          "x": 439,
          "y": 452
        },
        {
          "x": 438,
          "y": 451
        },
        {
          "x": 438,
          "y": 449
        },
        {
          "x": 437,
          "y": 448
        },
        {
          "x": 416,
          "y": 448
        },
        {
          "x": 416,
          "y": 449
        },
        {
          "x": 415,
          "y": 450
        },
        {
          "x": 415,
          "y": 452
        },
        {
          "x": 414,
          "y": 453
        },
        {
          "x": 414,
          "y": 454
        },
        {
          "x": 413,
          "y": 455
        },
        {
          "x": 413,
          "y": 456
        },
        {
          "x": 412,
          "y": 457
        },
        {
          "x": 412,
          "y": 459
        },
        {
          "x": 411,
          "y": 460
        },
        {
          "x": 411,
          "y": 462
        },
        {
          "x": 410,
          "y": 463
        },
        {
          "x": 410,
          "y": 466
        },
        {
          "x": 409,
          "y": 467
        },
        {
          "x": 409,
          "y": 471
        },
        {
          "x": 410,
          "y": 472
        },
        {
          "x": 410,
          "y": 484
        },
        {
          "x": 411,
          "y": 485
        },
        {
          "x": 411,
          "y": 490
        },
        {
          "x": 412,
          "y": 491
        },
        {
          "x": 411,
          "y": 492
        },
        {
          "x": 411,
          "y": 497
        },
        {
          "x": 410,
          "y": 498
        },
        {
          "x": 410,
          "y": 505
        },
        {
          "x": 409,
          "y": 506
        },
        {
          "x": 409,
          "y": 511
        },
        {
          "x": 410,
          "y": 512
        },
        {
          "x": 410,
          "y": 518
        },
        {
          "x": 411,
          "y": 519
        },
        {
          "x": 411,
          "y": 521
        },
        {
          "x": 412,
          "y": 522
        },
        {
          "x": 412,
          "y": 523
        },
        {
          "x": 413,
          "y": 524
        },
        {
          "x": 413,
          "y": 527
        }
      ],
      "attributes": {
        "fingerHint": "unknown",
        "shape": "unknown",
        "quality": 4,
        "occluded": false,
        "artificialTip": false,
        "annotationMethod": "vision-reviewed-yolo-real-prelabel-v2",
        "confidence": 0.739023,
        "reviewRequired": false
      }
    },
    {
      "id": "n5",
      "label": "nail_texture",
      "polygon": [
        {
          "x": 228,
          "y": 273
        },
        {
          "x": 228,
          "y": 274
        },
        {
          "x": 227,
          "y": 275
        },
        {
          "x": 227,
          "y": 276
        },
        {
          "x": 222,
          "y": 281
        },
        {
          "x": 221,
          "y": 281
        },
        {
          "x": 218,
          "y": 284
        },
        {
          "x": 218,
          "y": 285
        },
        {
          "x": 211,
          "y": 292
        },
        {
          "x": 211,
          "y": 293
        },
        {
          "x": 205,
          "y": 299
        },
        {
          "x": 205,
          "y": 300
        },
        {
          "x": 203,
          "y": 302
        },
        {
          "x": 203,
          "y": 303
        },
        {
          "x": 201,
          "y": 305
        },
        {
          "x": 201,
          "y": 306
        },
        {
          "x": 200,
          "y": 307
        },
        {
          "x": 200,
          "y": 309
        },
        {
          "x": 199,
          "y": 310
        },
        {
          "x": 199,
          "y": 312
        },
        {
          "x": 198,
          "y": 313
        },
        {
          "x": 198,
          "y": 315
        },
        {
          "x": 197,
          "y": 316
        },
        {
          "x": 197,
          "y": 317
        },
        {
          "x": 196,
          "y": 318
        },
        {
          "x": 196,
          "y": 319
        },
        {
          "x": 192,
          "y": 323
        },
        {
          "x": 192,
          "y": 325
        },
        {
          "x": 191,
          "y": 326
        },
        {
          "x": 191,
          "y": 350
        },
        {
          "x": 192,
          "y": 351
        },
        {
          "x": 192,
          "y": 353
        },
        {
          "x": 193,
          "y": 354
        },
        {
          "x": 193,
          "y": 355
        },
        {
          "x": 194,
          "y": 356
        },
        {
          "x": 194,
          "y": 357
        },
        {
          "x": 195,
          "y": 358
        },
        {
          "x": 195,
          "y": 359
        },
        {
          "x": 197,
          "y": 361
        },
        {
          "x": 197,
          "y": 362
        },
        {
          "x": 200,
          "y": 365
        },
        {
          "x": 200,
          "y": 366
        },
        {
          "x": 206,
          "y": 372
        },
        {
          "x": 206,
          "y": 373
        },
        {
          "x": 208,
          "y": 375
        },
        {
          "x": 208,
          "y": 376
        },
        {
          "x": 214,
          "y": 382
        },
        {
          "x": 215,
          "y": 382
        },
        {
          "x": 220,
          "y": 387
        },
        {
          "x": 221,
          "y": 387
        },
        {
          "x": 227,
          "y": 393
        },
        {
          "x": 228,
          "y": 393
        },
        {
          "x": 229,
          "y": 394
        },
        {
          "x": 230,
          "y": 394
        },
        {
          "x": 231,
          "y": 395
        },
        {
          "x": 232,
          "y": 395
        },
        {
          "x": 233,
          "y": 396
        },
        {
          "x": 234,
          "y": 396
        },
        {
          "x": 235,
          "y": 397
        },
        {
          "x": 237,
          "y": 397
        },
        {
          "x": 238,
          "y": 398
        },
        {
          "x": 239,
          "y": 398
        },
        {
          "x": 240,
          "y": 399
        },
        {
          "x": 241,
          "y": 399
        },
        {
          "x": 242,
          "y": 400
        },
        {
          "x": 243,
          "y": 400
        },
        {
          "x": 244,
          "y": 401
        },
        {
          "x": 307,
          "y": 401
        },
        {
          "x": 308,
          "y": 400
        },
        {
          "x": 309,
          "y": 400
        },
        {
          "x": 310,
          "y": 399
        },
        {
          "x": 311,
          "y": 399
        },
        {
          "x": 312,
          "y": 398
        },
        {
          "x": 313,
          "y": 398
        },
        {
          "x": 315,
          "y": 396
        },
        {
          "x": 316,
          "y": 396
        },
        {
          "x": 320,
          "y": 392
        },
        {
          "x": 321,
          "y": 392
        },
        {
          "x": 323,
          "y": 390
        },
        {
          "x": 324,
          "y": 390
        },
        {
          "x": 329,
          "y": 385
        },
        {
          "x": 329,
          "y": 346
        },
        {
          "x": 328,
          "y": 345
        },
        {
          "x": 328,
          "y": 344
        },
        {
          "x": 327,
          "y": 343
        },
        {
          "x": 327,
          "y": 342
        },
        {
          "x": 326,
          "y": 341
        },
        {
          "x": 326,
          "y": 339
        },
        {
          "x": 325,
          "y": 338
        },
        {
          "x": 325,
          "y": 337
        },
        {
          "x": 322,
          "y": 334
        },
        {
          "x": 322,
          "y": 333
        },
        {
          "x": 320,
          "y": 331
        },
        {
          "x": 320,
          "y": 330
        },
        {
          "x": 318,
          "y": 328
        },
        {
          "x": 318,
          "y": 327
        },
        {
          "x": 316,
          "y": 325
        },
        {
          "x": 316,
          "y": 324
        },
        {
          "x": 311,
          "y": 319
        },
        {
          "x": 311,
          "y": 318
        },
        {
          "x": 306,
          "y": 313
        },
        {
          "x": 305,
          "y": 313
        },
        {
          "x": 301,
          "y": 309
        },
        {
          "x": 301,
          "y": 308
        },
        {
          "x": 300,
          "y": 307
        },
        {
          "x": 299,
          "y": 307
        },
        {
          "x": 296,
          "y": 304
        },
        {
          "x": 295,
          "y": 304
        },
        {
          "x": 291,
          "y": 300
        },
        {
          "x": 290,
          "y": 300
        },
        {
          "x": 288,
          "y": 298
        },
        {
          "x": 287,
          "y": 298
        },
        {
          "x": 285,
          "y": 296
        },
        {
          "x": 284,
          "y": 296
        },
        {
          "x": 283,
          "y": 295
        },
        {
          "x": 282,
          "y": 295
        },
        {
          "x": 281,
          "y": 294
        },
        {
          "x": 280,
          "y": 294
        },
        {
          "x": 277,
          "y": 291
        },
        {
          "x": 276,
          "y": 291
        },
        {
          "x": 274,
          "y": 289
        },
        {
          "x": 273,
          "y": 289
        },
        {
          "x": 270,
          "y": 286
        },
        {
          "x": 269,
          "y": 286
        },
        {
          "x": 258,
          "y": 275
        },
        {
          "x": 258,
          "y": 274
        },
        {
          "x": 257,
          "y": 273
        }
      ],
      "attributes": {
        "fingerHint": "unknown",
        "shape": "unknown",
        "quality": 4,
        "occluded": false,
        "artificialTip": false,
        "annotationMethod": "vision-reviewed-yolo-real-prelabel-v2",
        "confidence": 0.736154,
        "reviewRequired": false
      }
    },
    {
      "id": "n6",
      "label": "nail_texture",
      "polygon": [
        {
          "x": 718,
          "y": 606
        },
        {
          "x": 725,
          "y": 606
        },
        {
          "x": 724,
          "y": 605
        },
        {
          "x": 723,
          "y": 605
        },
        {
          "x": 722,
          "y": 606
        },
        {
          "x": 718,
          "y": 606
        },
        {
          "x": 714,
          "y": 599
        },
        {
          "x": 718,
          "y": 595
        },
        {
          "x": 719,
          "y": 595
        },
        {
          "x": 720,
          "y": 594
        },
        {
          "x": 721,
          "y": 594
        },
        {
          "x": 722,
          "y": 593
        },
        {
          "x": 723,
          "y": 593
        },
        {
          "x": 724,
          "y": 592
        },
        {
          "x": 725,
          "y": 592
        },
        {
          "x": 729,
          "y": 588
        },
        {
          "x": 729,
          "y": 587
        },
        {
          "x": 730,
          "y": 586
        },
        {
          "x": 730,
          "y": 585
        },
        {
          "x": 731,
          "y": 584
        },
        {
          "x": 731,
          "y": 494
        },
        {
          "x": 730,
          "y": 493
        },
        {
          "x": 730,
          "y": 491
        },
        {
          "x": 729,
          "y": 490
        },
        {
          "x": 729,
          "y": 489
        },
        {
          "x": 728,
          "y": 488
        },
        {
          "x": 728,
          "y": 487
        },
        {
          "x": 727,
          "y": 486
        },
        {
          "x": 727,
          "y": 485
        },
        {
          "x": 722,
          "y": 480
        },
        {
          "x": 722,
          "y": 479
        },
        {
          "x": 720,
          "y": 477
        },
        {
          "x": 720,
          "y": 476
        },
        {
          "x": 719,
          "y": 475
        },
        {
          "x": 719,
          "y": 474
        },
        {
          "x": 718,
          "y": 473
        },
        {
          "x": 718,
          "y": 472
        },
        {
          "x": 717,
          "y": 471
        },
        {
          "x": 717,
          "y": 470
        },
        {
          "x": 716,
          "y": 469
        },
        {
          "x": 716,
          "y": 468
        },
        {
          "x": 715,
          "y": 467
        },
        {
          "x": 715,
          "y": 466
        },
        {
          "x": 712,
          "y": 463
        },
        {
          "x": 712,
          "y": 462
        },
        {
          "x": 709,
          "y": 459
        },
        {
          "x": 709,
          "y": 458
        },
        {
          "x": 708,
          "y": 457
        },
        {
          "x": 684,
          "y": 457
        },
        {
          "x": 683,
          "y": 458
        },
        {
          "x": 683,
          "y": 459
        },
        {
          "x": 680,
          "y": 462
        },
        {
          "x": 679,
          "y": 462
        },
        {
          "x": 675,
          "y": 466
        },
        {
          "x": 674,
          "y": 466
        },
        {
          "x": 674,
          "y": 467
        },
        {
          "x": 666,
          "y": 475
        },
        {
          "x": 666,
          "y": 476
        },
        {
          "x": 665,
          "y": 477
        },
        {
          "x": 665,
          "y": 478
        },
        {
          "x": 663,
          "y": 480
        },
        {
          "x": 663,
          "y": 481
        },
        {
          "x": 660,
          "y": 484
        },
        {
          "x": 660,
          "y": 485
        },
        {
          "x": 657,
          "y": 488
        },
        {
          "x": 657,
          "y": 489
        },
        {
          "x": 654,
          "y": 492
        },
        {
          "x": 654,
          "y": 493
        },
        {
          "x": 653,
          "y": 494
        },
        {
          "x": 653,
          "y": 495
        },
        {
          "x": 649,
          "y": 499
        },
        {
          "x": 648,
          "y": 499
        },
        {
          "x": 648,
          "y": 500
        },
        {
          "x": 646,
          "y": 502
        },
        {
          "x": 646,
          "y": 503
        },
        {
          "x": 644,
          "y": 505
        },
        {
          "x": 643,
          "y": 504
        },
        {
          "x": 643,
          "y": 501
        },
        {
          "x": 642,
          "y": 500
        },
        {
          "x": 642,
          "y": 498
        },
        {
          "x": 641,
          "y": 497
        },
        {
          "x": 641,
          "y": 496
        },
        {
          "x": 640,
          "y": 495
        },
        {
          "x": 640,
          "y": 493
        },
        {
          "x": 639,
          "y": 492
        },
        {
          "x": 639,
          "y": 490
        },
        {
          "x": 638,
          "y": 489
        },
        {
          "x": 638,
          "y": 488
        },
        {
          "x": 637,
          "y": 487
        },
        {
          "x": 637,
          "y": 486
        },
        {
          "x": 637,
          "y": 541
        },
        {
          "x": 637,
          "y": 538
        },
        {
          "x": 638,
          "y": 537
        },
        {
          "x": 638,
          "y": 535
        },
        {
          "x": 639,
          "y": 534
        },
        {
          "x": 639,
          "y": 531
        },
        {
          "x": 640,
          "y": 530
        },
        {
          "x": 640,
          "y": 528
        },
        {
          "x": 641,
          "y": 527
        },
        {
          "x": 641,
          "y": 526
        },
        {
          "x": 642,
          "y": 525
        },
        {
          "x": 642,
          "y": 523
        },
        {
          "x": 643,
          "y": 522
        },
        {
          "x": 643,
          "y": 519
        },
        {
          "x": 644,
          "y": 518
        },
        {
          "x": 645,
          "y": 519
        },
        {
          "x": 645,
          "y": 520
        },
        {
          "x": 646,
          "y": 521
        },
        {
          "x": 646,
          "y": 523
        },
        {
          "x": 647,
          "y": 524
        },
        {
          "x": 647,
          "y": 525
        },
        {
          "x": 648,
          "y": 526
        },
        {
          "x": 648,
          "y": 530
        },
        {
          "x": 649,
          "y": 531
        },
        {
          "x": 649,
          "y": 540
        },
        {
          "x": 648,
          "y": 541
        },
        {
          "x": 648,
          "y": 547
        },
        {
          "x": 647,
          "y": 548
        },
        {
          "x": 647,
          "y": 551
        },
        {
          "x": 646,
          "y": 552
        },
        {
          "x": 646,
          "y": 556
        },
        {
          "x": 645,
          "y": 557
        },
        {
          "x": 645,
          "y": 562
        },
        {
          "x": 644,
          "y": 563
        },
        {
          "x": 644,
          "y": 571
        },
        {
          "x": 645,
          "y": 572
        },
        {
          "x": 645,
          "y": 574
        },
        {
          "x": 646,
          "y": 575
        },
        {
          "x": 646,
          "y": 576
        },
        {
          "x": 647,
          "y": 577
        },
        {
          "x": 647,
          "y": 579
        },
        {
          "x": 655,
          "y": 587
        },
        {
          "x": 655,
          "y": 588
        },
        {
          "x": 656,
          "y": 589
        },
        {
          "x": 657,
          "y": 589
        },
        {
          "x": 660,
          "y": 592
        },
        {
          "x": 661,
          "y": 592
        },
        {
          "x": 663,
          "y": 594
        },
        {
          "x": 664,
          "y": 594
        },
        {
          "x": 666,
          "y": 596
        },
        {
          "x": 666,
          "y": 597
        },
        {
          "x": 668,
          "y": 599
        },
        {
          "x": 669,
          "y": 599
        },
        {
          "x": 670,
          "y": 600
        },
        {
          "x": 671,
          "y": 600
        },
        {
          "x": 673,
          "y": 602
        },
        {
          "x": 674,
          "y": 602
        },
        {
          "x": 675,
          "y": 603
        },
        {
          "x": 676,
          "y": 603
        },
        {
          "x": 679,
          "y": 606
        },
        {
          "x": 697,
          "y": 606
        },
        {
          "x": 696,
          "y": 605
        },
        {
          "x": 696,
          "y": 604
        },
        {
          "x": 697,
          "y": 603
        },
        {
          "x": 699,
          "y": 603
        },
        {
          "x": 700,
          "y": 602
        },
        {
          "x": 703,
          "y": 602
        },
        {
          "x": 704,
          "y": 601
        },
        {
          "x": 706,
          "y": 601
        },
        {
          "x": 707,
          "y": 600
        },
        {
          "x": 709,
          "y": 600
        },
        {
          "x": 710,
          "y": 599
        },
        {
          "x": 714,
          "y": 599
        }
      ],
      "attributes": {
        "fingerHint": "unknown",
        "shape": "unknown",
        "quality": 4,
        "occluded": false,
        "artificialTip": false,
        "annotationMethod": "vision-reviewed-yolo-real-prelabel-v2",
        "confidence": 0.719351,
        "reviewRequired": false
      }
    },
    {
      "id": "n7",
      "label": "nail_texture",
      "polygon": [
        {
          "x": 843,
          "y": 558
        },
        {
          "x": 843,
          "y": 574
        },
        {
          "x": 843,
          "y": 558
        },
        {
          "x": 856,
          "y": 557
        },
        {
          "x": 857,
          "y": 558
        },
        {
          "x": 857,
          "y": 562
        },
        {
          "x": 858,
          "y": 563
        },
        {
          "x": 858,
          "y": 565
        },
        {
          "x": 859,
          "y": 566
        },
        {
          "x": 859,
          "y": 568
        },
        {
          "x": 860,
          "y": 569
        },
        {
          "x": 860,
          "y": 570
        },
        {
          "x": 861,
          "y": 571
        },
        {
          "x": 861,
          "y": 573
        },
        {
          "x": 862,
          "y": 574
        },
        {
          "x": 862,
          "y": 576
        },
        {
          "x": 863,
          "y": 577
        },
        {
          "x": 863,
          "y": 580
        },
        {
          "x": 864,
          "y": 581
        },
        {
          "x": 864,
          "y": 583
        },
        {
          "x": 865,
          "y": 584
        },
        {
          "x": 865,
          "y": 586
        },
        {
          "x": 866,
          "y": 587
        },
        {
          "x": 866,
          "y": 588
        },
        {
          "x": 867,
          "y": 589
        },
        {
          "x": 867,
          "y": 590
        },
        {
          "x": 868,
          "y": 591
        },
        {
          "x": 868,
          "y": 592
        },
        {
          "x": 869,
          "y": 593
        },
        {
          "x": 869,
          "y": 594
        },
        {
          "x": 870,
          "y": 595
        },
        {
          "x": 870,
          "y": 598
        },
        {
          "x": 871,
          "y": 599
        },
        {
          "x": 871,
          "y": 601
        },
        {
          "x": 872,
          "y": 602
        },
        {
          "x": 872,
          "y": 604
        },
        {
          "x": 873,
          "y": 605
        },
        {
          "x": 873,
          "y": 606
        },
        {
          "x": 874,
          "y": 607
        },
        {
          "x": 874,
          "y": 608
        },
        {
          "x": 876,
          "y": 610
        },
        {
          "x": 876,
          "y": 611
        },
        {
          "x": 877,
          "y": 612
        },
        {
          "x": 877,
          "y": 613
        },
        {
          "x": 878,
          "y": 614
        },
        {
          "x": 878,
          "y": 615
        },
        {
          "x": 884,
          "y": 621
        },
        {
          "x": 885,
          "y": 621
        },
        {
          "x": 887,
          "y": 623
        },
        {
          "x": 888,
          "y": 623
        },
        {
          "x": 889,
          "y": 624
        },
        {
          "x": 890,
          "y": 624
        },
        {
          "x": 891,
          "y": 625
        },
        {
          "x": 892,
          "y": 625
        },
        {
          "x": 893,
          "y": 626
        },
        {
          "x": 895,
          "y": 626
        },
        {
          "x": 896,
          "y": 627
        },
        {
          "x": 929,
          "y": 627
        },
        {
          "x": 930,
          "y": 626
        },
        {
          "x": 931,
          "y": 626
        },
        {
          "x": 934,
          "y": 623
        },
        {
          "x": 934,
          "y": 622
        },
        {
          "x": 937,
          "y": 619
        },
        {
          "x": 937,
          "y": 618
        },
        {
          "x": 943,
          "y": 612
        },
        {
          "x": 943,
          "y": 611
        },
        {
          "x": 945,
          "y": 609
        },
        {
          "x": 945,
          "y": 608
        },
        {
          "x": 949,
          "y": 604
        },
        {
          "x": 949,
          "y": 603
        },
        {
          "x": 950,
          "y": 602
        },
        {
          "x": 950,
          "y": 542
        },
        {
          "x": 949,
          "y": 541
        },
        {
          "x": 949,
          "y": 540
        },
        {
          "x": 947,
          "y": 538
        },
        {
          "x": 947,
          "y": 537
        },
        {
          "x": 946,
          "y": 536
        },
        {
          "x": 946,
          "y": 535
        },
        {
          "x": 945,
          "y": 534
        },
        {
          "x": 945,
          "y": 533
        },
        {
          "x": 944,
          "y": 532
        },
        {
          "x": 944,
          "y": 531
        },
        {
          "x": 943,
          "y": 530
        },
        {
          "x": 943,
          "y": 529
        },
        {
          "x": 942,
          "y": 528
        },
        {
          "x": 942,
          "y": 527
        },
        {
          "x": 941,
          "y": 526
        },
        {
          "x": 941,
          "y": 525
        },
        {
          "x": 939,
          "y": 523
        },
        {
          "x": 939,
          "y": 522
        },
        {
          "x": 937,
          "y": 520
        },
        {
          "x": 937,
          "y": 519
        },
        {
          "x": 936,
          "y": 518
        },
        {
          "x": 936,
          "y": 517
        },
        {
          "x": 935,
          "y": 516
        },
        {
          "x": 935,
          "y": 515
        },
        {
          "x": 934,
          "y": 514
        },
        {
          "x": 934,
          "y": 513
        },
        {
          "x": 933,
          "y": 512
        },
        {
          "x": 933,
          "y": 511
        },
        {
          "x": 932,
          "y": 510
        },
        {
          "x": 932,
          "y": 509
        },
        {
          "x": 930,
          "y": 507
        },
        {
          "x": 930,
          "y": 506
        },
        {
          "x": 928,
          "y": 504
        },
        {
          "x": 928,
          "y": 503
        },
        {
          "x": 926,
          "y": 501
        },
        {
          "x": 926,
          "y": 500
        },
        {
          "x": 920,
          "y": 494
        },
        {
          "x": 920,
          "y": 493
        },
        {
          "x": 911,
          "y": 484
        },
        {
          "x": 911,
          "y": 483
        },
        {
          "x": 909,
          "y": 481
        },
        {
          "x": 909,
          "y": 480
        },
        {
          "x": 880,
          "y": 480
        },
        {
          "x": 878,
          "y": 482
        },
        {
          "x": 877,
          "y": 482
        },
        {
          "x": 876,
          "y": 483
        },
        {
          "x": 876,
          "y": 484
        },
        {
          "x": 865,
          "y": 495
        },
        {
          "x": 865,
          "y": 496
        },
        {
          "x": 861,
          "y": 500
        },
        {
          "x": 861,
          "y": 502
        },
        {
          "x": 860,
          "y": 503
        },
        {
          "x": 860,
          "y": 505
        },
        {
          "x": 859,
          "y": 506
        },
        {
          "x": 859,
          "y": 511
        },
        {
          "x": 858,
          "y": 512
        },
        {
          "x": 858,
          "y": 524
        },
        {
          "x": 857,
          "y": 525
        },
        {
          "x": 857,
          "y": 531
        },
        {
          "x": 856,
          "y": 532
        },
        {
          "x": 856,
          "y": 539
        },
        {
          "x": 855,
          "y": 540
        },
        {
          "x": 855,
          "y": 550
        },
        {
          "x": 856,
          "y": 551
        },
        {
          "x": 856,
          "y": 557
        }
      ],
      "attributes": {
        "fingerHint": "unknown",
        "shape": "unknown",
        "quality": 4,
        "occluded": false,
        "artificialTip": false,
        "annotationMethod": "vision-reviewed-yolo-real-prelabel-v2",
        "confidence": 0.653901,
        "reviewRequired": false
      }
    },
    {
      "id": "n8",
      "label": "nail_texture",
      "polygon": [
        {
          "x": 349,
          "y": 449
        },
        {
          "x": 346,
          "y": 452
        },
        {
          "x": 346,
          "y": 453
        },
        {
          "x": 336,
          "y": 463
        },
        {
          "x": 336,
          "y": 464
        },
        {
          "x": 332,
          "y": 468
        },
        {
          "x": 332,
          "y": 469
        },
        {
          "x": 330,
          "y": 471
        },
        {
          "x": 330,
          "y": 472
        },
        {
          "x": 329,
          "y": 473
        },
        {
          "x": 329,
          "y": 474
        },
        {
          "x": 328,
          "y": 475
        },
        {
          "x": 328,
          "y": 476
        },
        {
          "x": 327,
          "y": 477
        },
        {
          "x": 327,
          "y": 478
        },
        {
          "x": 326,
          "y": 479
        },
        {
          "x": 326,
          "y": 480
        },
        {
          "x": 323,
          "y": 483
        },
        {
          "x": 323,
          "y": 484
        },
        {
          "x": 321,
          "y": 486
        },
        {
          "x": 321,
          "y": 487
        },
        {
          "x": 320,
          "y": 488
        },
        {
          "x": 320,
          "y": 489
        },
        {
          "x": 318,
          "y": 491
        },
        {
          "x": 318,
          "y": 492
        },
        {
          "x": 317,
          "y": 493
        },
        {
          "x": 317,
          "y": 495
        },
        {
          "x": 316,
          "y": 496
        },
        {
          "x": 316,
          "y": 498
        },
        {
          "x": 315,
          "y": 499
        },
        {
          "x": 315,
          "y": 542
        },
        {
          "x": 316,
          "y": 543
        },
        {
          "x": 316,
          "y": 546
        },
        {
          "x": 317,
          "y": 547
        },
        {
          "x": 317,
          "y": 549
        },
        {
          "x": 318,
          "y": 550
        },
        {
          "x": 318,
          "y": 552
        },
        {
          "x": 319,
          "y": 553
        },
        {
          "x": 319,
          "y": 555
        },
        {
          "x": 320,
          "y": 556
        },
        {
          "x": 320,
          "y": 558
        },
        {
          "x": 321,
          "y": 559
        },
        {
          "x": 321,
          "y": 560
        },
        {
          "x": 322,
          "y": 561
        },
        {
          "x": 322,
          "y": 562
        },
        {
          "x": 323,
          "y": 563
        },
        {
          "x": 323,
          "y": 564
        },
        {
          "x": 325,
          "y": 566
        },
        {
          "x": 325,
          "y": 567
        },
        {
          "x": 334,
          "y": 576
        },
        {
          "x": 335,
          "y": 576
        },
        {
          "x": 338,
          "y": 579
        },
        {
          "x": 339,
          "y": 579
        },
        {
          "x": 343,
          "y": 583
        },
        {
          "x": 396,
          "y": 583
        },
        {
          "x": 396,
          "y": 498
        },
        {
          "x": 395,
          "y": 497
        },
        {
          "x": 395,
          "y": 495
        },
        {
          "x": 394,
          "y": 494
        },
        {
          "x": 394,
          "y": 491
        },
        {
          "x": 393,
          "y": 490
        },
        {
          "x": 393,
          "y": 486
        },
        {
          "x": 392,
          "y": 485
        },
        {
          "x": 392,
          "y": 481
        },
        {
          "x": 391,
          "y": 480
        },
        {
          "x": 391,
          "y": 476
        },
        {
          "x": 390,
          "y": 475
        },
        {
          "x": 390,
          "y": 473
        },
        {
          "x": 389,
          "y": 472
        },
        {
          "x": 389,
          "y": 470
        },
        {
          "x": 388,
          "y": 469
        },
        {
          "x": 388,
          "y": 468
        },
        {
          "x": 386,
          "y": 466
        },
        {
          "x": 386,
          "y": 465
        },
        {
          "x": 384,
          "y": 463
        },
        {
          "x": 384,
          "y": 462
        },
        {
          "x": 382,
          "y": 460
        },
        {
          "x": 382,
          "y": 459
        },
        {
          "x": 381,
          "y": 458
        },
        {
          "x": 381,
          "y": 457
        },
        {
          "x": 376,
          "y": 452
        },
        {
          "x": 376,
          "y": 451
        },
        {
          "x": 375,
          "y": 450
        },
        {
          "x": 375,
          "y": 449
        }
      ],
      "attributes": {
        "fingerHint": "unknown",
        "shape": "unknown",
        "quality": 4,
        "occluded": false,
        "artificialTip": false,
        "annotationMethod": "vision-reviewed-yolo-real-prelabel-v2",
        "confidence": 0.638075,
        "reviewRequired": false
      }
    },
    {
      "id": "n9",
      "label": "nail_texture",
      "polygon": [
        {
          "x": 612,
          "y": 480
        },
        {
          "x": 611,
          "y": 481
        },
        {
          "x": 611,
          "y": 482
        },
        {
          "x": 602,
          "y": 491
        },
        {
          "x": 602,
          "y": 492
        },
        {
          "x": 597,
          "y": 497
        },
        {
          "x": 596,
          "y": 497
        },
        {
          "x": 593,
          "y": 500
        },
        {
          "x": 593,
          "y": 501
        },
        {
          "x": 588,
          "y": 506
        },
        {
          "x": 588,
          "y": 507
        },
        {
          "x": 586,
          "y": 509
        },
        {
          "x": 586,
          "y": 510
        },
        {
          "x": 585,
          "y": 511
        },
        {
          "x": 585,
          "y": 512
        },
        {
          "x": 583,
          "y": 514
        },
        {
          "x": 583,
          "y": 515
        },
        {
          "x": 581,
          "y": 517
        },
        {
          "x": 581,
          "y": 518
        },
        {
          "x": 579,
          "y": 520
        },
        {
          "x": 579,
          "y": 521
        },
        {
          "x": 577,
          "y": 523
        },
        {
          "x": 577,
          "y": 524
        },
        {
          "x": 575,
          "y": 526
        },
        {
          "x": 575,
          "y": 527
        },
        {
          "x": 574,
          "y": 528
        },
        {
          "x": 574,
          "y": 529
        },
        {
          "x": 571,
          "y": 532
        },
        {
          "x": 571,
          "y": 533
        },
        {
          "x": 570,
          "y": 534
        },
        {
          "x": 570,
          "y": 535
        },
        {
          "x": 569,
          "y": 536
        },
        {
          "x": 569,
          "y": 581
        },
        {
          "x": 572,
          "y": 581
        },
        {
          "x": 573,
          "y": 582
        },
        {
          "x": 574,
          "y": 582
        },
        {
          "x": 577,
          "y": 585
        },
        {
          "x": 578,
          "y": 585
        },
        {
          "x": 579,
          "y": 586
        },
        {
          "x": 580,
          "y": 586
        },
        {
          "x": 583,
          "y": 589
        },
        {
          "x": 583,
          "y": 590
        },
        {
          "x": 586,
          "y": 593
        },
        {
          "x": 587,
          "y": 593
        },
        {
          "x": 590,
          "y": 596
        },
        {
          "x": 590,
          "y": 597
        },
        {
          "x": 591,
          "y": 598
        },
        {
          "x": 623,
          "y": 598
        },
        {
          "x": 623,
          "y": 594
        },
        {
          "x": 624,
          "y": 593
        },
        {
          "x": 624,
          "y": 591
        },
        {
          "x": 625,
          "y": 590
        },
        {
          "x": 625,
          "y": 588
        },
        {
          "x": 626,
          "y": 587
        },
        {
          "x": 626,
          "y": 586
        },
        {
          "x": 627,
          "y": 585
        },
        {
          "x": 627,
          "y": 583
        },
        {
          "x": 628,
          "y": 582
        },
        {
          "x": 628,
          "y": 581
        },
        {
          "x": 629,
          "y": 580
        },
        {
          "x": 629,
          "y": 578
        },
        {
          "x": 630,
          "y": 577
        },
        {
          "x": 630,
          "y": 574
        },
        {
          "x": 631,
          "y": 573
        },
        {
          "x": 631,
          "y": 570
        },
        {
          "x": 632,
          "y": 569
        },
        {
          "x": 632,
          "y": 564
        },
        {
          "x": 633,
          "y": 563
        },
        {
          "x": 633,
          "y": 559
        },
        {
          "x": 634,
          "y": 558
        },
        {
          "x": 634,
          "y": 555
        },
        {
          "x": 635,
          "y": 554
        },
        {
          "x": 635,
          "y": 552
        },
        {
          "x": 636,
          "y": 551
        },
        {
          "x": 636,
          "y": 550
        },
        {
          "x": 637,
          "y": 549
        },
        {
          "x": 637,
          "y": 547
        },
        {
          "x": 638,
          "y": 546
        },
        {
          "x": 638,
          "y": 544
        },
        {
          "x": 639,
          "y": 543
        },
        {
          "x": 639,
          "y": 540
        },
        {
          "x": 640,
          "y": 539
        },
        {
          "x": 640,
          "y": 537
        },
        {
          "x": 641,
          "y": 536
        },
        {
          "x": 641,
          "y": 534
        },
        {
          "x": 642,
          "y": 533
        },
        {
          "x": 642,
          "y": 531
        },
        {
          "x": 643,
          "y": 530
        },
        {
          "x": 643,
          "y": 498
        },
        {
          "x": 642,
          "y": 497
        },
        {
          "x": 642,
          "y": 495
        },
        {
          "x": 641,
          "y": 494
        },
        {
          "x": 641,
          "y": 492
        },
        {
          "x": 640,
          "y": 491
        },
        {
          "x": 640,
          "y": 489
        },
        {
          "x": 639,
          "y": 488
        },
        {
          "x": 639,
          "y": 486
        },
        {
          "x": 638,
          "y": 485
        },
        {
          "x": 638,
          "y": 484
        },
        {
          "x": 637,
          "y": 483
        },
        {
          "x": 637,
          "y": 482
        },
        {
          "x": 635,
          "y": 480
        }
      ],
      "attributes": {
        "fingerHint": "unknown",
        "shape": "unknown",
        "quality": 4,
        "occluded": false,
        "artificialTip": false,
        "annotationMethod": "vision-reviewed-yolo-real-prelabel-v2",
        "confidence": 0.504503,
        "reviewRequired": false
      }
    },
    {
      "id": "n10",
      "label": "nail_texture",
      "polygon": [
        {
          "x": 961,
          "y": 196
        },
        {
          "x": 961,
          "y": 199
        },
        {
          "x": 957,
          "y": 203
        },
        {
          "x": 957,
          "y": 204
        },
        {
          "x": 961,
          "y": 204
        },
        {
          "x": 961,
          "y": 196
        },
        {
          "x": 888,
          "y": 272
        },
        {
          "x": 887,
          "y": 272
        },
        {
          "x": 886,
          "y": 273
        },
        {
          "x": 885,
          "y": 273
        },
        {
          "x": 884,
          "y": 274
        },
        {
          "x": 880,
          "y": 274
        },
        {
          "x": 879,
          "y": 275
        },
        {
          "x": 877,
          "y": 275
        },
        {
          "x": 876,
          "y": 276
        },
        {
          "x": 875,
          "y": 276
        },
        {
          "x": 874,
          "y": 277
        },
        {
          "x": 872,
          "y": 277
        },
        {
          "x": 871,
          "y": 278
        },
        {
          "x": 870,
          "y": 278
        },
        {
          "x": 869,
          "y": 279
        },
        {
          "x": 867,
          "y": 279
        },
        {
          "x": 866,
          "y": 280
        },
        {
          "x": 865,
          "y": 280
        },
        {
          "x": 863,
          "y": 282
        },
        {
          "x": 862,
          "y": 282
        },
        {
          "x": 861,
          "y": 283
        },
        {
          "x": 861,
          "y": 285
        },
        {
          "x": 863,
          "y": 287
        },
        {
          "x": 844,
          "y": 287
        },
        {
          "x": 844,
          "y": 286
        },
        {
          "x": 845,
          "y": 285
        },
        {
          "x": 846,
          "y": 285
        },
        {
          "x": 847,
          "y": 284
        },
        {
          "x": 847,
          "y": 283
        },
        {
          "x": 846,
          "y": 282
        },
        {
          "x": 846,
          "y": 281
        },
        {
          "x": 844,
          "y": 279
        },
        {
          "x": 844,
          "y": 277
        },
        {
          "x": 841,
          "y": 274
        },
        {
          "x": 840,
          "y": 274
        },
        {
          "x": 839,
          "y": 273
        },
        {
          "x": 838,
          "y": 273
        },
        {
          "x": 837,
          "y": 272
        },
        {
          "x": 836,
          "y": 272
        },
        {
          "x": 835,
          "y": 271
        },
        {
          "x": 833,
          "y": 271
        },
        {
          "x": 832,
          "y": 270
        },
        {
          "x": 830,
          "y": 270
        },
        {
          "x": 829,
          "y": 269
        },
        {
          "x": 824,
          "y": 269
        },
        {
          "x": 823,
          "y": 268
        },
        {
          "x": 818,
          "y": 268
        },
        {
          "x": 817,
          "y": 267
        },
        {
          "x": 813,
          "y": 267
        },
        {
          "x": 812,
          "y": 266
        },
        {
          "x": 809,
          "y": 266
        },
        {
          "x": 808,
          "y": 267
        },
        {
          "x": 803,
          "y": 267
        },
        {
          "x": 802,
          "y": 266
        },
        {
          "x": 797,
          "y": 266
        },
        {
          "x": 796,
          "y": 265
        },
        {
          "x": 794,
          "y": 265
        },
        {
          "x": 793,
          "y": 264
        },
        {
          "x": 791,
          "y": 264
        },
        {
          "x": 790,
          "y": 263
        },
        {
          "x": 789,
          "y": 263
        },
        {
          "x": 785,
          "y": 259
        },
        {
          "x": 785,
          "y": 258
        },
        {
          "x": 784,
          "y": 257
        },
        {
          "x": 784,
          "y": 256
        },
        {
          "x": 783,
          "y": 255
        },
        {
          "x": 783,
          "y": 254
        },
        {
          "x": 782,
          "y": 253
        },
        {
          "x": 782,
          "y": 252
        },
        {
          "x": 781,
          "y": 251
        },
        {
          "x": 781,
          "y": 250
        },
        {
          "x": 780,
          "y": 249
        },
        {
          "x": 780,
          "y": 248
        },
        {
          "x": 779,
          "y": 247
        },
        {
          "x": 779,
          "y": 246
        },
        {
          "x": 778,
          "y": 245
        },
        {
          "x": 778,
          "y": 244
        },
        {
          "x": 777,
          "y": 243
        },
        {
          "x": 777,
          "y": 242
        },
        {
          "x": 776,
          "y": 241
        },
        {
          "x": 776,
          "y": 240
        },
        {
          "x": 775,
          "y": 239
        },
        {
          "x": 775,
          "y": 238
        },
        {
          "x": 774,
          "y": 237
        },
        {
          "x": 774,
          "y": 236
        },
        {
          "x": 772,
          "y": 234
        },
        {
          "x": 772,
          "y": 233
        },
        {
          "x": 771,
          "y": 232
        },
        {
          "x": 771,
          "y": 231
        },
        {
          "x": 770,
          "y": 230
        },
        {
          "x": 770,
          "y": 229
        },
        {
          "x": 769,
          "y": 228
        },
        {
          "x": 769,
          "y": 225
        },
        {
          "x": 768,
          "y": 224
        },
        {
          "x": 768,
          "y": 217
        },
        {
          "x": 767,
          "y": 216
        },
        {
          "x": 767,
          "y": 211
        },
        {
          "x": 768,
          "y": 210
        },
        {
          "x": 768,
          "y": 204
        },
        {
          "x": 769,
          "y": 203
        },
        {
          "x": 769,
          "y": 199
        },
        {
          "x": 770,
          "y": 198
        },
        {
          "x": 770,
          "y": 194
        },
        {
          "x": 771,
          "y": 193
        },
        {
          "x": 771,
          "y": 190
        },
        {
          "x": 772,
          "y": 189
        },
        {
          "x": 772,
          "y": 186
        },
        {
          "x": 773,
          "y": 185
        },
        {
          "x": 773,
          "y": 184
        },
        {
          "x": 774,
          "y": 183
        },
        {
          "x": 774,
          "y": 182
        },
        {
          "x": 776,
          "y": 180
        },
        {
          "x": 776,
          "y": 179
        },
        {
          "x": 779,
          "y": 176
        },
        {
          "x": 779,
          "y": 175
        },
        {
          "x": 783,
          "y": 171
        },
        {
          "x": 783,
          "y": 169
        },
        {
          "x": 784,
          "y": 168
        },
        {
          "x": 784,
          "y": 167
        },
        {
          "x": 785,
          "y": 166
        },
        {
          "x": 785,
          "y": 164
        },
        {
          "x": 786,
          "y": 163
        },
        {
          "x": 786,
          "y": 160
        },
        {
          "x": 787,
          "y": 159
        },
        {
          "x": 787,
          "y": 157
        },
        {
          "x": 788,
          "y": 156
        },
        {
          "x": 788,
          "y": 150
        },
        {
          "x": 789,
          "y": 151
        },
        {
          "x": 789,
          "y": 155
        },
        {
          "x": 790,
          "y": 156
        },
        {
          "x": 790,
          "y": 157
        },
        {
          "x": 791,
          "y": 158
        },
        {
          "x": 791,
          "y": 160
        },
        {
          "x": 792,
          "y": 161
        },
        {
          "x": 792,
          "y": 163
        },
        {
          "x": 795,
          "y": 166
        },
        {
          "x": 795,
          "y": 167
        },
        {
          "x": 796,
          "y": 168
        },
        {
          "x": 797,
          "y": 168
        },
        {
          "x": 799,
          "y": 170
        },
        {
          "x": 800,
          "y": 170
        },
        {
          "x": 802,
          "y": 172
        },
        {
          "x": 803,
          "y": 172
        },
        {
          "x": 804,
          "y": 173
        },
        {
          "x": 805,
          "y": 173
        },
        {
          "x": 806,
          "y": 174
        },
        {
          "x": 810,
          "y": 174
        },
        {
          "x": 811,
          "y": 175
        },
        {
          "x": 812,
          "y": 175
        },
        {
          "x": 813,
          "y": 174
        },
        {
          "x": 814,
          "y": 174
        },
        {
          "x": 815,
          "y": 173
        },
        {
          "x": 816,
          "y": 173
        },
        {
          "x": 817,
          "y": 172
        },
        {
          "x": 818,
          "y": 172
        },
        {
          "x": 819,
          "y": 171
        },
        {
          "x": 820,
          "y": 171
        },
        {
          "x": 822,
          "y": 169
        },
        {
          "x": 822,
          "y": 168
        },
        {
          "x": 823,
          "y": 167
        },
        {
          "x": 823,
          "y": 166
        },
        {
          "x": 825,
          "y": 164
        },
        {
          "x": 825,
          "y": 162
        },
        {
          "x": 826,
          "y": 161
        },
        {
          "x": 826,
          "y": 160
        },
        {
          "x": 827,
          "y": 159
        },
        {
          "x": 827,
          "y": 158
        },
        {
          "x": 828,
          "y": 157
        },
        {
          "x": 828,
          "y": 156
        },
        {
          "x": 829,
          "y": 155
        },
        {
          "x": 829,
          "y": 154
        },
        {
          "x": 830,
          "y": 153
        },
        {
          "x": 830,
          "y": 152
        },
        {
          "x": 831,
          "y": 151
        },
        {
          "x": 831,
          "y": 150
        },
        {
          "x": 832,
          "y": 149
        },
        {
          "x": 832,
          "y": 148
        },
        {
          "x": 833,
          "y": 147
        },
        {
          "x": 795,
          "y": 135
        },
        {
          "x": 798,
          "y": 135
        },
        {
          "x": 799,
          "y": 134
        },
        {
          "x": 804,
          "y": 134
        },
        {
          "x": 805,
          "y": 133
        },
        {
          "x": 806,
          "y": 133
        },
        {
          "x": 807,
          "y": 132
        },
        {
          "x": 808,
          "y": 132
        },
        {
          "x": 809,
          "y": 131
        },
        {
          "x": 809,
          "y": 130
        },
        {
          "x": 812,
          "y": 127
        },
        {
          "x": 793,
          "y": 127
        },
        {
          "x": 793,
          "y": 128
        },
        {
          "x": 792,
          "y": 129
        },
        {
          "x": 792,
          "y": 130
        },
        {
          "x": 791,
          "y": 131
        },
        {
          "x": 791,
          "y": 132
        },
        {
          "x": 793,
          "y": 134
        },
        {
          "x": 794,
          "y": 134
        },
        {
          "x": 795,
          "y": 135
        },
        {
          "x": 833,
          "y": 147
        },
        {
          "x": 833,
          "y": 146
        },
        {
          "x": 835,
          "y": 144
        },
        {
          "x": 835,
          "y": 143
        },
        {
          "x": 840,
          "y": 138
        },
        {
          "x": 840,
          "y": 137
        },
        {
          "x": 844,
          "y": 133
        },
        {
          "x": 845,
          "y": 133
        },
        {
          "x": 849,
          "y": 129
        },
        {
          "x": 850,
          "y": 129
        },
        {
          "x": 851,
          "y": 128
        },
        {
          "x": 852,
          "y": 128
        },
        {
          "x": 853,
          "y": 127
        },
        {
          "x": 947,
          "y": 127
        },
        {
          "x": 948,
          "y": 128
        },
        {
          "x": 951,
          "y": 128
        },
        {
          "x": 952,
          "y": 129
        },
        {
          "x": 955,
          "y": 129
        },
        {
          "x": 956,
          "y": 130
        },
        {
          "x": 957,
          "y": 130
        },
        {
          "x": 960,
          "y": 133
        },
        {
          "x": 961,
          "y": 133
        },
        {
          "x": 961,
          "y": 186
        },
        {
          "x": 957,
          "y": 186
        },
        {
          "x": 954,
          "y": 189
        },
        {
          "x": 954,
          "y": 190
        },
        {
          "x": 953,
          "y": 191
        },
        {
          "x": 951,
          "y": 191
        },
        {
          "x": 950,
          "y": 192
        },
        {
          "x": 948,
          "y": 192
        },
        {
          "x": 942,
          "y": 198
        },
        {
          "x": 941,
          "y": 198
        },
        {
          "x": 937,
          "y": 202
        },
        {
          "x": 937,
          "y": 203
        },
        {
          "x": 936,
          "y": 204
        },
        {
          "x": 936,
          "y": 205
        },
        {
          "x": 935,
          "y": 206
        },
        {
          "x": 935,
          "y": 207
        },
        {
          "x": 932,
          "y": 210
        },
        {
          "x": 932,
          "y": 211
        },
        {
          "x": 931,
          "y": 212
        },
        {
          "x": 931,
          "y": 214
        },
        {
          "x": 930,
          "y": 215
        },
        {
          "x": 930,
          "y": 216
        },
        {
          "x": 929,
          "y": 217
        },
        {
          "x": 929,
          "y": 218
        },
        {
          "x": 928,
          "y": 219
        },
        {
          "x": 928,
          "y": 221
        },
        {
          "x": 927,
          "y": 222
        },
        {
          "x": 927,
          "y": 224
        },
        {
          "x": 926,
          "y": 225
        },
        {
          "x": 926,
          "y": 226
        },
        {
          "x": 925,
          "y": 227
        },
        {
          "x": 925,
          "y": 229
        },
        {
          "x": 924,
          "y": 230
        },
        {
          "x": 924,
          "y": 236
        },
        {
          "x": 923,
          "y": 237
        },
        {
          "x": 923,
          "y": 239
        },
        {
          "x": 922,
          "y": 240
        },
        {
          "x": 922,
          "y": 242
        },
        {
          "x": 921,
          "y": 243
        },
        {
          "x": 921,
          "y": 244
        },
        {
          "x": 915,
          "y": 250
        },
        {
          "x": 915,
          "y": 251
        },
        {
          "x": 913,
          "y": 253
        },
        {
          "x": 912,
          "y": 253
        },
        {
          "x": 910,
          "y": 255
        },
        {
          "x": 909,
          "y": 255
        },
        {
          "x": 900,
          "y": 264
        },
        {
          "x": 899,
          "y": 264
        },
        {
          "x": 898,
          "y": 265
        },
        {
          "x": 897,
          "y": 265
        },
        {
          "x": 893,
          "y": 269
        },
        {
          "x": 892,
          "y": 269
        },
        {
          "x": 890,
          "y": 271
        },
        {
          "x": 889,
          "y": 271
        },
        {
          "x": 888,
          "y": 272
        }
      ],
      "attributes": {
        "fingerHint": "unknown",
        "shape": "unknown",
        "quality": 4,
        "occluded": false,
        "artificialTip": false,
        "annotationMethod": "vision-reviewed-yolo-real-prelabel-v2",
        "confidence": 0.377614,
        "reviewRequired": false
      }
    }
  ]
}